venSpeakerPy/__init__.py
venSpeakerPy/lib_helper.py
venSpeakerPy/lib_sl_text.py
venSpeakerPy/lib_speak.py
venspeakerpy-0.1.1.dist-info/licenses/LICENSE
venspeakerpy-0.1.1.dist-info/METADATA
venspeakerpy-0.1.1.dist-info/WHEEL
venspeakerpy-0.1.1.dist-info/top_level.txt
venspeakerpy-0.1.1.dist-info/RECORD
