Metadata-Version: 2.4
Name: venSpeakerPy
Version: 0.1.1
Summary: Python TTS package using Silero models for Russian language
Home-page: https://github.com/VenalusDev/ven-speaker-py
Author: VenalusDev
Author-email: Venalusdev@mail.ru
Classifier: Programming Language :: Python :: 3
Classifier: License :: OSI Approved :: MIT License
Classifier: Operating System :: OS Independent
Requires-Python: >=3.11
License-File: LICENSE
Requires-Dist: numpy>=1.24
Requires-Dist: scipy<2.0,>=1.10
Requires-Dist: sounddevice>=0.4.7
Requires-Dist: soundfile>=0.12.1
Requires-Dist: torch<3.0,>=2.1
Requires-Dist: nltk<4.0,>=3.9
Requires-Dist: num2words<0.6,>=0.5
Requires-Dist: transliterate>=1.10.2
Requires-Dist: silero>=0.4
Dynamic: author
Dynamic: author-email
Dynamic: classifier
Dynamic: description
Dynamic: description-content-type
Dynamic: home-page
Dynamic: license-file
Dynamic: requires-dist
Dynamic: requires-python
Dynamic: summary
